<?xml version="1.0"?>
<ResourceWrapperCache xmlns:xsi="http://www.w3.org/2001/XMLSchema-instance" xmlns:xsd="http://www.w3.org/2001/XMLSchema">
  <entries>
    <Entry>
      <resourcePath>start.lua</resourcePath>
      <resourceLastModified>0001-01-01T00:00:00</resourceLastModified>
      <resourceFileSize>0</resourceFileSize>
      <extraXmlLastModified>0001-01-01T00:00:00</extraXmlLastModified>
      <extraXmlFileSize>0</extraXmlFileSize>
    </Entry>
    <Entry>
      <id>7c73da9f-6790-4697-9be6-8392bc5bf41f</id>
      <resourcePath>StartScene.xml</resourcePath>
      <resourceLastModified>2015-12-26T13:45:53.075+08:00</resourceLastModified>
      <resourceFileSize>1511</resourceFileSize>
      <extraXmlLastModified>2015-12-26T13:45:53.117+08:00</extraXmlLastModified>
      <extraXmlFileSize>0</extraXmlFileSize>
    </Entry>
    <Entry>
      <resourcePath>SWFPlayer.lua</resourcePath>
      <resourceLastModified>0001-01-01T00:00:00</resourceLastModified>
      <resourceFileSize>0</resourceFileSize>
      <extraXmlLastModified>0001-01-01T00:00:00</extraXmlLastModified>
      <extraXmlFileSize>0</extraXmlFileSize>
    </Entry>
    <Entry>
      <id>c9e66558-91ac-45b8-9354-9e027404167b</id>
      <resourcePath>newEnemyTexture.xml</resourcePath>
      <resourceLastModified>2015-12-26T13:45:34.212+08:00</resourceLastModified>
      <resourceFileSize>24251</resourceFileSize>
      <extraXmlLastModified>2015-12-26T13:45:34.288+08:00</extraXmlLastModified>
      <extraXmlFileSize>0</extraXmlFileSize>
    </Entry>
    <Entry>
      <id>6aac7ec9-0588-437d-a122-4a95696ddaa1</id>
      <resourcePath>daodunbing0063.png</resourcePath>
      <resourceLastModified>2015-12-26T09:38:04.318+08:00</resourceLastModified>
      <resourceFileSize>18446</resourceFileSize>
      <extraXmlLastModified>2015-12-26T13:35:15.05+08:00</extraXmlLastModified>
      <extraXmlFileSize>2041</extraXmlFileSize>
    </Entry>
    <Entry>
      <id>4714b694-87c1-40e1-b543-1f0bc1649983</id>
      <resourcePath>daodunbing0062.png</resourcePath>
      <resourceLastModified>2015-12-26T09:38:04.19+08:00</resourceLastModified>
      <resourceFileSize>18800</resourceFileSize>
      <extraXmlLastModified>2015-12-26T13:35:15.019+08:00</extraXmlLastModified>
      <extraXmlFileSize>2041</extraXmlFileSize>
    </Entry>
    <Entry>
      <id>b1408417-0d45-4f81-8d5c-70dd7760fd36</id>
      <resourcePath>daodunbing0061.png</resourcePath>
      <resourceLastModified>2015-12-26T09:38:03.916+08:00</resourceLastModified>
      <resourceFileSize>19036</resourceFileSize>
      <extraXmlLastModified>2015-12-26T13:35:14.989+08:00</extraXmlLastModified>
      <extraXmlFileSize>2041</extraXmlFileSize>
    </Entry>
    <Entry>
      <id>2aaefa02-4eeb-4c6f-82c0-e6386e9216d3</id>
      <resourcePath>daodunbing0060.png</resourcePath>
      <resourceLastModified>2015-12-26T09:38:03.795+08:00</resourceLastModified>
      <resourceFileSize>18868</resourceFileSize>
      <extraXmlLastModified>2015-12-26T13:35:14.959+08:00</extraXmlLastModified>
      <extraXmlFileSize>2041</extraXmlFileSize>
    </Entry>
    <Entry>
      <id>38d2101d-8f62-42d9-a050-3b9eca1d123e</id>
      <resourcePath>daodunbing0059.png</resourcePath>
      <resourceLastModified>2015-12-26T09:38:03.668+08:00</resourceLastModified>
      <resourceFileSize>18766</resourceFileSize>
      <extraXmlLastModified>2015-12-26T13:35:14.93+08:00</extraXmlLastModified>
      <extraXmlFileSize>2041</extraXmlFileSize>
    </Entry>
    <Entry>
      <id>97365aba-f636-4e6e-8369-85f54ee40693</id>
      <resourcePath>daodunbing0058.png</resourcePath>
      <resourceLastModified>2015-12-26T09:38:03.446+08:00</resourceLastModified>
      <resourceFileSize>18830</resourceFileSize>
      <extraXmlLastModified>2015-12-26T13:35:14.9+08:00</extraXmlLastModified>
      <extraXmlFileSize>2041</extraXmlFileSize>
    </Entry>
    <Entry>
      <id>1e7c9fed-a7f2-43ef-978f-06769bf2a3e8</id>
      <resourcePath>daodunbing0057.png</resourcePath>
      <resourceLastModified>2015-12-26T09:38:03.319+08:00</resourceLastModified>
      <resourceFileSize>17932</resourceFileSize>
      <extraXmlLastModified>2015-12-26T13:35:14.874+08:00</extraXmlLastModified>
      <extraXmlFileSize>2035</extraXmlFileSize>
    </Entry>
    <Entry>
      <id>80415894-1afc-48b3-9a03-5f184da178eb</id>
      <resourcePath>daodunbing0056.png</resourcePath>
      <resourceLastModified>2015-12-26T09:38:03.17+08:00</resourceLastModified>
      <resourceFileSize>18012</resourceFileSize>
      <extraXmlLastModified>2015-12-26T13:35:14.845+08:00</extraXmlLastModified>
      <extraXmlFileSize>2035</extraXmlFileSize>
    </Entry>
    <Entry>
      <id>2ee7c3fe-a8fb-47ac-bd13-0a730be05982</id>
      <resourcePath>daodunbing0055.png</resourcePath>
      <resourceLastModified>2015-12-26T09:38:02.99+08:00</resourceLastModified>
      <resourceFileSize>17888</resourceFileSize>
      <extraXmlLastModified>2015-12-26T13:35:14.816+08:00</extraXmlLastModified>
      <extraXmlFileSize>2035</extraXmlFileSize>
    </Entry>
    <Entry>
      <id>f7281f2a-b6b0-44dd-99b1-cc3880f91da7</id>
      <resourcePath>daodunbing0054.png</resourcePath>
      <resourceLastModified>2015-12-26T09:38:02.865+08:00</resourceLastModified>
      <resourceFileSize>18047</resourceFileSize>
      <extraXmlLastModified>2015-12-26T13:35:14.79+08:00</extraXmlLastModified>
      <extraXmlFileSize>2035</extraXmlFileSize>
    </Entry>
    <Entry>
      <id>45081cbd-7deb-4b34-91fd-f4b0db276ee8</id>
      <resourcePath>daodunbing0053.png</resourcePath>
      <resourceLastModified>2015-12-26T09:38:02.742+08:00</resourceLastModified>
      <resourceFileSize>18091</resourceFileSize>
      <extraXmlLastModified>2015-12-26T13:35:14.764+08:00</extraXmlLastModified>
      <extraXmlFileSize>2035</extraXmlFileSize>
    </Entry>
    <Entry>
      <id>73aebe43-4ff0-42ad-829e-6ca1fd012763</id>
      <resourcePath>daodunbing0052.png</resourcePath>
      <resourceLastModified>2015-12-26T09:38:02.619+08:00</resourceLastModified>
      <resourceFileSize>18394</resourceFileSize>
      <extraXmlLastModified>2015-12-26T13:35:14.738+08:00</extraXmlLastModified>
      <extraXmlFileSize>2035</extraXmlFileSize>
    </Entry>
    <Entry>
      <id>c0935594-c5f0-426d-9f8f-f6e9e5d52cba</id>
      <resourcePath>daodunbing0051.png</resourcePath>
      <resourceLastModified>2015-12-26T09:38:02.438+08:00</resourceLastModified>
      <resourceFileSize>18874</resourceFileSize>
      <extraXmlLastModified>2015-12-26T13:35:14.712+08:00</extraXmlLastModified>
      <extraXmlFileSize>2035</extraXmlFileSize>
    </Entry>
    <Entry>
      <id>a1e4c6ff-8698-4234-9c5b-4efcd61e6a5a</id>
      <resourcePath>daodunbing0050.png</resourcePath>
      <resourceLastModified>2015-12-26T09:38:02.319+08:00</resourceLastModified>
      <resourceFileSize>18326</resourceFileSize>
      <extraXmlLastModified>2015-12-26T13:35:14.686+08:00</extraXmlLastModified>
      <extraXmlFileSize>2035</extraXmlFileSize>
    </Entry>
    <Entry>
      <id>16bfbed5-927d-4466-b5bf-fc5e75065a91</id>
      <resourcePath>daodunbing0049.png</resourcePath>
      <resourceLastModified>2015-12-26T09:38:02.174+08:00</resourceLastModified>
      <resourceFileSize>18449</resourceFileSize>
      <extraXmlLastModified>2015-12-26T13:35:14.661+08:00</extraXmlLastModified>
      <extraXmlFileSize>2041</extraXmlFileSize>
    </Entry>
    <Entry>
      <id>876a267f-049f-4129-b5e4-f58a161ae269</id>
      <resourcePath>daodunbing0048.png</resourcePath>
      <resourceLastModified>2015-12-26T09:38:01.938+08:00</resourceLastModified>
      <resourceFileSize>18282</resourceFileSize>
      <extraXmlLastModified>2015-12-26T13:35:14.635+08:00</extraXmlLastModified>
      <extraXmlFileSize>2035</extraXmlFileSize>
    </Entry>
    <Entry>
      <id>ae35071f-715a-4142-a076-c2cb965119f1</id>
      <resourcePath>daodunbing0047.png</resourcePath>
      <resourceLastModified>2015-12-26T09:38:01.816+08:00</resourceLastModified>
      <resourceFileSize>18282</resourceFileSize>
      <extraXmlLastModified>2015-12-26T13:35:14.61+08:00</extraXmlLastModified>
      <extraXmlFileSize>2035</extraXmlFileSize>
    </Entry>
    <Entry>
      <id>e292362d-cfe9-4970-aaa1-9213b627f906</id>
      <resourcePath>daodunbing0046.png</resourcePath>
      <resourceLastModified>2015-12-26T09:38:01.659+08:00</resourceLastModified>
      <resourceFileSize>18160</resourceFileSize>
      <extraXmlLastModified>2015-12-26T13:35:14.586+08:00</extraXmlLastModified>
      <extraXmlFileSize>2035</extraXmlFileSize>
    </Entry>
    <Entry>
      <id>960264b4-7116-4f12-8c2e-39b216bfd8de</id>
      <resourcePath>daodunbing0045.png</resourcePath>
      <resourceLastModified>2015-12-26T09:38:01.343+08:00</resourceLastModified>
      <resourceFileSize>17878</resourceFileSize>
      <extraXmlLastModified>2015-12-26T13:35:14.562+08:00</extraXmlLastModified>
      <extraXmlFileSize>2035</extraXmlFileSize>
    </Entry>
    <Entry>
      <id>4887ad5e-5fa6-4698-b12d-02fe1a73c9c4</id>
      <resourcePath>daodunbing0044.png</resourcePath>
      <resourceLastModified>2015-12-26T09:38:01.217+08:00</resourceLastModified>
      <resourceFileSize>17862</resourceFileSize>
      <extraXmlLastModified>2015-12-26T13:35:14.538+08:00</extraXmlLastModified>
      <extraXmlFileSize>2035</extraXmlFileSize>
    </Entry>
    <Entry>
      <id>32f7f3ff-f425-4232-b579-250a22e032a7</id>
      <resourcePath>daodunbing0043.png</resourcePath>
      <resourceLastModified>2015-12-26T09:38:00.971+08:00</resourceLastModified>
      <resourceFileSize>18098</resourceFileSize>
      <extraXmlLastModified>2015-12-26T13:35:14.516+08:00</extraXmlLastModified>
      <extraXmlFileSize>2035</extraXmlFileSize>
    </Entry>
    <Entry>
      <id>fa30d11b-e6a0-4644-b446-fabab308b50d</id>
      <resourcePath>daodunbing0042.png</resourcePath>
      <resourceLastModified>2015-12-26T09:38:00.842+08:00</resourceLastModified>
      <resourceFileSize>18250</resourceFileSize>
      <extraXmlLastModified>2015-12-26T13:35:14.493+08:00</extraXmlLastModified>
      <extraXmlFileSize>2035</extraXmlFileSize>
    </Entry>
    <Entry>
      <id>38474c6c-7b97-49d1-8633-b7925de10279</id>
      <resourcePath>daodunbing0041.png</resourcePath>
      <resourceLastModified>2015-12-26T09:38:00.692+08:00</resourceLastModified>
      <resourceFileSize>18210</resourceFileSize>
      <extraXmlLastModified>2015-12-26T13:35:14.465+08:00</extraXmlLastModified>
      <extraXmlFileSize>2035</extraXmlFileSize>
    </Entry>
    <Entry>
      <id>730cba72-7351-43a9-a268-3a1a5dda16ee</id>
      <resourcePath>daodunbing0040.png</resourcePath>
      <resourceLastModified>2015-12-26T09:38:00.432+08:00</resourceLastModified>
      <resourceFileSize>18179</resourceFileSize>
      <extraXmlLastModified>2015-12-26T13:35:14.441+08:00</extraXmlLastModified>
      <extraXmlFileSize>2035</extraXmlFileSize>
    </Entry>
    <Entry>
      <id>4a70e595-74ce-486b-8803-06f529e94a79</id>
      <resourcePath>daodunbing0039.png</resourcePath>
      <resourceLastModified>2015-12-26T09:38:00.308+08:00</resourceLastModified>
      <resourceFileSize>18255</resourceFileSize>
      <extraXmlLastModified>2015-12-26T13:35:14.4+08:00</extraXmlLastModified>
      <extraXmlFileSize>2035</extraXmlFileSize>
    </Entry>
    <Entry>
      <id>6093298d-7cdb-4bf5-8681-4294a2752d57</id>
      <resourcePath>daodunbing0038.png</resourcePath>
      <resourceLastModified>2015-12-26T09:38:00.182+08:00</resourceLastModified>
      <resourceFileSize>18252</resourceFileSize>
      <extraXmlLastModified>2015-12-26T13:35:14.364+08:00</extraXmlLastModified>
      <extraXmlFileSize>2035</extraXmlFileSize>
    </Entry>
    <Entry>
      <id>a8a9e052-5b4d-4be9-8ba2-6421a592a5a8</id>
      <resourcePath>daodunbing0037.png</resourcePath>
      <resourceLastModified>2015-12-26T09:38:00.053+08:00</resourceLastModified>
      <resourceFileSize>18139</resourceFileSize>
      <extraXmlLastModified>2015-12-26T13:35:14.307+08:00</extraXmlLastModified>
      <extraXmlFileSize>2035</extraXmlFileSize>
    </Entry>
    <Entry>
      <id>14cd2fe2-7422-4173-a200-cdb7188588de</id>
      <resourcePath>daodunbing0036.png</resourcePath>
      <resourceLastModified>2015-12-26T09:37:59.914+08:00</resourceLastModified>
      <resourceFileSize>17712</resourceFileSize>
      <extraXmlLastModified>2015-12-26T13:35:14.275+08:00</extraXmlLastModified>
      <extraXmlFileSize>2035</extraXmlFileSize>
    </Entry>
    <Entry>
      <id>8f6cfbf8-1533-475e-82f8-b293353a35eb</id>
      <resourcePath>daodunbing0035.png</resourcePath>
      <resourceLastModified>2015-12-26T09:37:59.751+08:00</resourceLastModified>
      <resourceFileSize>17716</resourceFileSize>
      <extraXmlLastModified>2015-12-26T13:35:14.244+08:00</extraXmlLastModified>
      <extraXmlFileSize>2035</extraXmlFileSize>
    </Entry>
    <Entry>
      <id>b63cc644-291a-4e9c-92fa-512b8b9176d2</id>
      <resourcePath>daodunbing0034.png</resourcePath>
      <resourceLastModified>2015-12-26T09:37:59.578+08:00</resourceLastModified>
      <resourceFileSize>18282</resourceFileSize>
      <extraXmlLastModified>2015-12-26T13:35:14.218+08:00</extraXmlLastModified>
      <extraXmlFileSize>2035</extraXmlFileSize>
    </Entry>
    <Entry>
      <id>05707332-0743-4c6e-b2d6-3e3911f3c039</id>
      <resourcePath>daodunbing0033.png</resourcePath>
      <resourceLastModified>2015-12-26T09:37:59.36+08:00</resourceLastModified>
      <resourceFileSize>12295</resourceFileSize>
      <extraXmlLastModified>2015-12-26T13:35:14.185+08:00</extraXmlLastModified>
      <extraXmlFileSize>2035</extraXmlFileSize>
    </Entry>
    <Entry>
      <id>cbd5a9f8-c757-4908-86d2-b9c8a08efdee</id>
      <resourcePath>daodunbing0032.png</resourcePath>
      <resourceLastModified>2015-12-26T09:37:59.153+08:00</resourceLastModified>
      <resourceFileSize>12733</resourceFileSize>
      <extraXmlLastModified>2015-12-26T13:35:14.163+08:00</extraXmlLastModified>
      <extraXmlFileSize>2035</extraXmlFileSize>
    </Entry>
    <Entry>
      <id>cdc8c699-430a-427d-a034-c9f6b686ca5a</id>
      <resourcePath>daodunbing0031.png</resourcePath>
      <resourceLastModified>2015-12-26T09:37:59.008+08:00</resourceLastModified>
      <resourceFileSize>13243</resourceFileSize>
      <extraXmlLastModified>2015-12-26T13:35:14.142+08:00</extraXmlLastModified>
      <extraXmlFileSize>2035</extraXmlFileSize>
    </Entry>
    <Entry>
      <id>75a33684-c385-408c-a3bc-e10141e20f89</id>
      <resourcePath>daodunbing0030.png</resourcePath>
      <resourceLastModified>2015-12-26T09:37:58.863+08:00</resourceLastModified>
      <resourceFileSize>13919</resourceFileSize>
      <extraXmlLastModified>2015-12-26T13:35:14.077+08:00</extraXmlLastModified>
      <extraXmlFileSize>2035</extraXmlFileSize>
    </Entry>
    <Entry>
      <id>72623732-cc27-4382-bd3c-a0c88e6a0bdd</id>
      <resourcePath>daodunbing0029.png</resourcePath>
      <resourceLastModified>2015-12-26T09:37:58.72+08:00</resourceLastModified>
      <resourceFileSize>15091</resourceFileSize>
      <extraXmlLastModified>2015-12-26T13:35:14.046+08:00</extraXmlLastModified>
      <extraXmlFileSize>2035</extraXmlFileSize>
    </Entry>
    <Entry>
      <id>2e51d766-f1f0-42f4-b34c-cdc2a1754177</id>
      <resourcePath>daodunbing0028.png</resourcePath>
      <resourceLastModified>2015-12-26T09:37:58.581+08:00</resourceLastModified>
      <resourceFileSize>16216</resourceFileSize>
      <extraXmlLastModified>2015-12-26T13:35:14.021+08:00</extraXmlLastModified>
      <extraXmlFileSize>2035</extraXmlFileSize>
    </Entry>
    <Entry>
      <id>c18eb7c7-35eb-49b6-8445-74dbebbe6c26</id>
      <resourcePath>daodunbing0027.png</resourcePath>
      <resourceLastModified>2015-12-26T09:37:58.436+08:00</resourceLastModified>
      <resourceFileSize>16291</resourceFileSize>
      <extraXmlLastModified>2015-12-26T13:35:13.956+08:00</extraXmlLastModified>
      <extraXmlFileSize>2035</extraXmlFileSize>
    </Entry>
    <Entry>
      <id>d9d5eacf-eef9-405a-8e8d-a5a97ef32b9d</id>
      <resourcePath>daodunbing0026.png</resourcePath>
      <resourceLastModified>2015-12-26T09:37:58.247+08:00</resourceLastModified>
      <resourceFileSize>15269</resourceFileSize>
      <extraXmlLastModified>2015-12-26T13:35:13.759+08:00</extraXmlLastModified>
      <extraXmlFileSize>2035</extraXmlFileSize>
    </Entry>
    <Entry>
      <id>2550cc7a-a9d2-4c9c-b93c-16c296c3a691</id>
      <resourcePath>daodunbing0025.png</resourcePath>
      <resourceLastModified>2015-12-26T09:37:58.099+08:00</resourceLastModified>
      <resourceFileSize>14575</resourceFileSize>
      <extraXmlLastModified>2015-12-26T13:35:13.568+08:00</extraXmlLastModified>
      <extraXmlFileSize>2035</extraXmlFileSize>
    </Entry>
    <Entry>
      <id>7ed48d86-ea07-496c-92f7-4e6ca79f0de5</id>
      <resourcePath>daodunbing0024.png</resourcePath>
      <resourceLastModified>2015-12-26T09:37:57.951+08:00</resourceLastModified>
      <resourceFileSize>13231</resourceFileSize>
      <extraXmlLastModified>2015-12-26T13:35:13.538+08:00</extraXmlLastModified>
      <extraXmlFileSize>2035</extraXmlFileSize>
    </Entry>
    <Entry>
      <id>0b094922-f969-4f08-acbf-c063c7c03241</id>
      <resourcePath>daodunbing0023.png</resourcePath>
      <resourceLastModified>2015-12-26T09:37:57.81+08:00</resourceLastModified>
      <resourceFileSize>12644</resourceFileSize>
      <extraXmlLastModified>2015-12-26T13:35:13.514+08:00</extraXmlLastModified>
      <extraXmlFileSize>2035</extraXmlFileSize>
    </Entry>
    <Entry>
      <id>96987baa-76c6-4099-af91-8da8a408daf2</id>
      <resourcePath>daodunbing0022.png</resourcePath>
      <resourceLastModified>2015-12-26T09:37:57.661+08:00</resourceLastModified>
      <resourceFileSize>12308</resourceFileSize>
      <extraXmlLastModified>2015-12-26T13:35:13.491+08:00</extraXmlLastModified>
      <extraXmlFileSize>2035</extraXmlFileSize>
    </Entry>
    <Entry>
      <id>3368642d-bd12-4fa5-bf14-0abc295047aa</id>
      <resourcePath>daodunbing0021.png</resourcePath>
      <resourceLastModified>2015-12-26T09:37:57.509+08:00</resourceLastModified>
      <resourceFileSize>18282</resourceFileSize>
      <extraXmlLastModified>2015-12-26T13:35:13.47+08:00</extraXmlLastModified>
      <extraXmlFileSize>2035</extraXmlFileSize>
    </Entry>
    <Entry>
      <id>5f81b5f4-b0b1-451d-bc98-c222ff2c3c90</id>
      <resourcePath>daodunbing0020.png</resourcePath>
      <resourceLastModified>2015-12-26T09:37:57.16+08:00</resourceLastModified>
      <resourceFileSize>18213</resourceFileSize>
      <extraXmlLastModified>2015-12-26T13:35:13.448+08:00</extraXmlLastModified>
      <extraXmlFileSize>2035</extraXmlFileSize>
    </Entry>
    <Entry>
      <id>24f4056f-deca-4f8a-ae1a-c59e31d46c27</id>
      <resourcePath>daodunbing0019.png</resourcePath>
      <resourceLastModified>2015-12-26T09:37:57.005+08:00</resourceLastModified>
      <resourceFileSize>18228</resourceFileSize>
      <extraXmlLastModified>2015-12-26T13:35:13.425+08:00</extraXmlLastModified>
      <extraXmlFileSize>2035</extraXmlFileSize>
    </Entry>
    <Entry>
      <id>f2984f7e-ec61-4693-9583-42c2887f696f</id>
      <resourcePath>daodunbing0018.png</resourcePath>
      <resourceLastModified>2015-12-26T09:37:56.85+08:00</resourceLastModified>
      <resourceFileSize>18055</resourceFileSize>
      <extraXmlLastModified>2015-12-26T13:35:13.402+08:00</extraXmlLastModified>
      <extraXmlFileSize>2035</extraXmlFileSize>
    </Entry>
    <Entry>
      <id>b4b20533-9d2b-4808-8161-85d4e0ef95fa</id>
      <resourcePath>daodunbing0017.png</resourcePath>
      <resourceLastModified>2015-12-26T09:37:56.687+08:00</resourceLastModified>
      <resourceFileSize>17998</resourceFileSize>
      <extraXmlLastModified>2015-12-26T13:35:13.379+08:00</extraXmlLastModified>
      <extraXmlFileSize>2035</extraXmlFileSize>
    </Entry>
    <Entry>
      <id>e1225587-8a06-48a2-9459-b8f4dd47f6ff</id>
      <resourcePath>daodunbing0016.png</resourcePath>
      <resourceLastModified>2015-12-26T09:37:56.523+08:00</resourceLastModified>
      <resourceFileSize>17948</resourceFileSize>
      <extraXmlLastModified>2015-12-26T13:35:13.35+08:00</extraXmlLastModified>
      <extraXmlFileSize>2035</extraXmlFileSize>
    </Entry>
    <Entry>
      <id>98387962-6254-4144-a70a-337ce7df53e0</id>
      <resourcePath>daodunbing0015.png</resourcePath>
      <resourceLastModified>2015-12-26T09:37:56.331+08:00</resourceLastModified>
      <resourceFileSize>17910</resourceFileSize>
      <extraXmlLastModified>2015-12-26T13:35:13.329+08:00</extraXmlLastModified>
      <extraXmlFileSize>2035</extraXmlFileSize>
    </Entry>
    <Entry>
      <id>b44557d9-081e-4514-b20d-10f890c06741</id>
      <resourcePath>daodunbing0014.png</resourcePath>
      <resourceLastModified>2015-12-26T09:37:56.168+08:00</resourceLastModified>
      <resourceFileSize>17905</resourceFileSize>
      <extraXmlLastModified>2015-12-26T13:35:13.311+08:00</extraXmlLastModified>
      <extraXmlFileSize>2035</extraXmlFileSize>
    </Entry>
    <Entry>
      <id>ef895bf5-8e88-46d4-8075-0640e1a3374a</id>
      <resourcePath>daodunbing0013.png</resourcePath>
      <resourceLastModified>2015-12-26T09:37:55.958+08:00</resourceLastModified>
      <resourceFileSize>17850</resourceFileSize>
      <extraXmlLastModified>2015-12-26T13:35:13.292+08:00</extraXmlLastModified>
      <extraXmlFileSize>2035</extraXmlFileSize>
    </Entry>
    <Entry>
      <id>b6d3355a-170c-4645-8790-9d3f90bd5c4f</id>
      <resourcePath>daodunbing0012.png</resourcePath>
      <resourceLastModified>2015-12-26T09:37:54.782+08:00</resourceLastModified>
      <resourceFileSize>17819</resourceFileSize>
      <extraXmlLastModified>2015-12-26T13:35:13.275+08:00</extraXmlLastModified>
      <extraXmlFileSize>2035</extraXmlFileSize>
    </Entry>
    <Entry>
      <id>f5301560-8d43-456a-869a-6a626599a7ab</id>
      <resourcePath>daodunbing0011.png</resourcePath>
      <resourceLastModified>2015-12-26T09:37:54.277+08:00</resourceLastModified>
      <resourceFileSize>17663</resourceFileSize>
      <extraXmlLastModified>2015-12-26T13:35:13.257+08:00</extraXmlLastModified>
      <extraXmlFileSize>2035</extraXmlFileSize>
    </Entry>
    <Entry>
      <id>7d6148fe-0706-4bbf-8b0a-a999f9122e3f</id>
      <resourcePath>daodunbing0010.png</resourcePath>
      <resourceLastModified>2015-12-26T09:37:53.755+08:00</resourceLastModified>
      <resourceFileSize>17852</resourceFileSize>
      <extraXmlLastModified>2015-12-26T13:35:13.242+08:00</extraXmlLastModified>
      <extraXmlFileSize>2035</extraXmlFileSize>
    </Entry>
    <Entry>
      <id>6a60b3dc-724e-4951-a454-81ef1f3a5d07</id>
      <resourcePath>daodunbing0009.png</resourcePath>
      <resourceLastModified>2015-12-26T09:37:52.958+08:00</resourceLastModified>
      <resourceFileSize>17826</resourceFileSize>
      <extraXmlLastModified>2015-12-26T13:35:13.226+08:00</extraXmlLastModified>
      <extraXmlFileSize>2035</extraXmlFileSize>
    </Entry>
    <Entry>
      <id>c955f81e-918b-45f4-a97c-def55e776c4c</id>
      <resourcePath>daodunbing0008.png</resourcePath>
      <resourceLastModified>2015-12-26T09:37:52.281+08:00</resourceLastModified>
      <resourceFileSize>17870</resourceFileSize>
      <extraXmlLastModified>2015-12-26T13:35:13.208+08:00</extraXmlLastModified>
      <extraXmlFileSize>2035</extraXmlFileSize>
    </Entry>
    <Entry>
      <id>8d71d91d-d933-43c1-ac15-a9b67cf8f374</id>
      <resourcePath>daodunbing0007.png</resourcePath>
      <resourceLastModified>2015-12-26T09:37:51.64+08:00</resourceLastModified>
      <resourceFileSize>17980</resourceFileSize>
      <extraXmlLastModified>2015-12-26T13:35:13.193+08:00</extraXmlLastModified>
      <extraXmlFileSize>2035</extraXmlFileSize>
    </Entry>
    <Entry>
      <id>77165100-6bfa-4058-8408-8628f6f7c967</id>
      <resourcePath>daodunbing0006.png</resourcePath>
      <resourceLastModified>2015-12-26T09:37:51.128+08:00</resourceLastModified>
      <resourceFileSize>18001</resourceFileSize>
      <extraXmlLastModified>2015-12-26T13:35:13.178+08:00</extraXmlLastModified>
      <extraXmlFileSize>2035</extraXmlFileSize>
    </Entry>
    <Entry>
      <id>49c3068f-05dc-4cb4-94ca-3080c12f2d34</id>
      <resourcePath>daodunbing0005.png</resourcePath>
      <resourceLastModified>2015-12-26T09:37:50.386+08:00</resourceLastModified>
      <resourceFileSize>18113</resourceFileSize>
      <extraXmlLastModified>2015-12-26T13:35:13.163+08:00</extraXmlLastModified>
      <extraXmlFileSize>2035</extraXmlFileSize>
    </Entry>
    <Entry>
      <id>12bacf13-6279-4a29-a1b7-702cd05fb134</id>
      <resourcePath>daodunbing0004.png</resourcePath>
      <resourceLastModified>2015-12-26T09:37:48.93+08:00</resourceLastModified>
      <resourceFileSize>18110</resourceFileSize>
      <extraXmlLastModified>2015-12-26T13:35:13.15+08:00</extraXmlLastModified>
      <extraXmlFileSize>2035</extraXmlFileSize>
    </Entry>
    <Entry>
      <id>68e1e0a7-775f-4f0d-97ba-535774cbd5b7</id>
      <resourcePath>daodunbing0003.png</resourcePath>
      <resourceLastModified>2015-12-26T09:37:47.413+08:00</resourceLastModified>
      <resourceFileSize>18191</resourceFileSize>
      <extraXmlLastModified>2015-12-26T13:35:13.136+08:00</extraXmlLastModified>
      <extraXmlFileSize>2035</extraXmlFileSize>
    </Entry>
    <Entry>
      <id>29675f7d-2081-43f7-851e-6e78a0344cbc</id>
      <resourcePath>daodunbing0002.png</resourcePath>
      <resourceLastModified>2015-12-26T09:37:45.727+08:00</resourceLastModified>
      <resourceFileSize>18274</resourceFileSize>
      <extraXmlLastModified>2015-12-26T13:35:13.123+08:00</extraXmlLastModified>
      <extraXmlFileSize>2035</extraXmlFileSize>
    </Entry>
    <Entry>
      <id>22f2e533-4801-441c-981c-340c61c0949c</id>
      <resourcePath>daodunbing0001.png</resourcePath>
      <resourceLastModified>2015-12-26T09:37:44.773+08:00</resourceLastModified>
      <resourceFileSize>18282</resourceFileSize>
      <extraXmlLastModified>2015-12-26T13:35:13.11+08:00</extraXmlLastModified>
      <extraXmlFileSize>2035</extraXmlFileSize>
    </Entry>
    <Entry>
      <id>0cdc85e0-bb49-4253-b395-851e5f82b89e</id>
      <resourcePath>daodunbing0067.png</resourcePath>
      <resourceLastModified>2015-12-26T09:38:04.962+08:00</resourceLastModified>
      <resourceFileSize>18282</resourceFileSize>
      <extraXmlLastModified>2015-12-26T13:35:13.098+08:00</extraXmlLastModified>
      <extraXmlFileSize>2035</extraXmlFileSize>
    </Entry>
    <Entry>
      <id>07da268d-fb65-4531-b06b-d753f415b72b</id>
      <resourcePath>daodunbing0066.png</resourcePath>
      <resourceLastModified>2015-12-26T09:38:04.837+08:00</resourceLastModified>
      <resourceFileSize>18282</resourceFileSize>
      <extraXmlLastModified>2015-12-26T13:35:15.147+08:00</extraXmlLastModified>
      <extraXmlFileSize>2035</extraXmlFileSize>
    </Entry>
    <Entry>
      <id>7472caa6-ae45-4502-9a93-2a7a61c5d4c1</id>
      <resourcePath>daodunbing0065.png</resourcePath>
      <resourceLastModified>2015-12-26T09:38:04.707+08:00</resourceLastModified>
      <resourceFileSize>18282</resourceFileSize>
      <extraXmlLastModified>2015-12-26T13:35:15.116+08:00</extraXmlLastModified>
      <extraXmlFileSize>2035</extraXmlFileSize>
    </Entry>
    <Entry>
      <id>bc9f48a1-84e1-4a82-85c7-3f30b7fed273</id>
      <resourcePath>daodunbing0064.png</resourcePath>
      <resourceLastModified>2015-12-26T09:38:04.45+08:00</resourceLastModified>
      <resourceFileSize>18327</resourceFileSize>
      <extraXmlLastModified>2015-12-26T13:35:15.085+08:00</extraXmlLastModified>
      <extraXmlFileSize>2041</extraXmlFileSize>
    </Entry>
    <Entry>
      <resourcePath>enemy.flash.swf</resourcePath>
      <resourceLastModified>0001-01-01T00:00:00</resourceLastModified>
      <resourceFileSize>0</resourceFileSize>
      <extraXmlLastModified>0001-01-01T00:00:00</extraXmlLastModified>
      <extraXmlFileSize>0</extraXmlFileSize>
    </Entry>
  </entries>
</ResourceWrapperCache>